Workbook

Sheet 🏠 Pyrux
A1: PYRUX — PANEL OPERATIVO
A2: Actualizado: | B2: =TEXT(TODAY(),"DD/MM/YYYY") -> 28/03/2026
A4: 💸 ESTADO FINANCIERO
B5: MRR Bruto (USD) | C5: Comisión MP | D5: MRR Neto (USD) | E5: Gastos / mes (USD) | F5: Resultado (USD)
A6: Valores | B6: =SUMIF('🤝 CRM (datos)'!O5:O100,"Activo",'🤝 CRM (datos)'!J5:J100) -> 20 | C6: =ROUND(B6*'⚙️ Config'!$B$6,2) -> 0.3 | D6: =ROUND(B6-C6,2) -> 19.7 | E6: =-'⚙️ Config'!$B$17 -> -31.3 | F6: =ROUND(D6+E6,2) -> -11.6
A7: Notas | B7: =IFERROR(__xludf.DUMMYFUNCTION("IF(B11=0,""Sin clientes"",IFERROR(JOIN("", "",FILTER('🤝 CRM (datos)'!B5:B100,'🤝 CRM (datos)'!O5:O100=""Activo"")),""—""))"),"MedMind") -> MedMind | C7: Débito auto 1.52% | D7: Ingreso real | E7: GWS + Claude + Dominios | F7: =IF(F6>=0,"SUPERÁVIT ✓","EN DÉFICIT ⚠️") -> EN DÉFICIT ⚠️
A9: 📊 PIPELINE DE VENTAS
B10: Clientes activos | C10: Prospectos identificados | D10: Contactados | E10: Propuestas enviadas | F10: Cerrados (últimos 60d)
A11: Actual | B11: =COUNTIF('🤝 CRM (datos)'!O5:O100,"Activo") -> 1 | C11: =COUNTA('📋 Prospectos Rosario'!A5:A200) -> 30 | D11: =COUNTIFS('📋 Prospectos Rosario'!J5:J200,"<>Sin contactar",'📋 Prospectos Rosario'!J5:J200,"<>") -> 15 | E11: =COUNTIF('📊 CRM — Pipeline'!I5:I100,"3 — Propuesta enviada")+COUNTIF('📊 CRM — Pipeline'!I5:I100,"4 — Negociación")+COUNTIF('📊 CRM — Pipeline'!I5:I100,"5 — GANADO ✓") -> #REF! | F11: =COUNTIF('📊 CRM — Pipeline'!I5:I100,"5 — GANADO ✓") -> #REF!
A12: Notas | B12: =IFERROR(__xludf.DUMMYFUNCTION("IF(B11=0,""—"",IFERROR(JOIN("", "",FILTER('🤝 CRM (datos)'!B5:B100,'🤝 CRM (datos)'!O5:O100=""Activo"")),""—""))"),"MedMind") -> MedMind | C12: Base Rosario | D12: =IF(D11=0,"Sin iniciar",D11&" contactado(s)") -> 15 contactado(s) | E12: =IF(E11=0,"—",E11&" enviada(s)") -> #REF! | F12: =IF(F11=0,"—",F11&" cliente(s)") -> #REF!
A14: 🎟️ CUPOS DESCUENTO DESARROLLO
B15: Cupos totales | C15: Usados | D15: Disponibles | E15: Descuento | F15: Aplica a
A16: Estado | B16: ='⚙️ Config'!$B$9 -> 5 | C16: ='⚙️ Config'!$B$10 -> 0 | D16: =B16-C16 -> 5 | E16: 30% sobre desarrollo | F16: Solo desarrollo (mant. sin descuento)
A18: ⚠️ ALERTAS
A19: CRÍTICO 🔴 | B19: MedMind sin contrato formal — riesgo de disputas o impago
A20: CRÍTICO 🔴 | B20: Empresa informal (sin CUIT/monotributo) — evaluar al escalar
A21: URGENTE 🟠 | B21: =IF(D11=0,"0 prospectos contactados — iniciar outreach",D11&" prospecto(s) contactado(s) — pipeline activo") -> 15 prospecto(s) contactado(s) — pipeline activo
A22: DÉFICIT 🟠 | B22: =IF(F6>=0,"Resultado mensual: $"&TEXT(F6,"0.00")&" USD — superávit ✓","Resultado mensual: -$"&TEXT(ABS(F6),"0.00")&" USD — en déficit") -> Resultado mensual: -$11.60 USD — en déficit
A23: FECHA 🟡 | B23: Dominio goalplanner.com.ar vence 12/02/2027 — renovar a tiempo
A24: FECHA 🟡 | B24: Dominio pyrux.com.ar vence 25/02/2027
A25: FECHA 🟡 | B25: Dominio medmind.com.ar vence 03/03/2027
A27: 📌 PRÓXIMAS ACCIONES
A28: # | B28: Acción | C28: Prioridad | D28: Responsable | E28: Estado
A29: 1 | B29: Completar ficha MedMind (monto dev, contacto, fecha inicio mantenimiento) | C29: ALTA | D29: Gino / Juan | E29: ⬜ Pendiente
A30: 2 | B30: Formalizar acuerdo MedMind (contrato escrito o email confirmatorio) | C30: ALTA | D30: Gino / Juan | E30: ⬜ Pendiente
A31: 3 | B31: Iniciar outreach prospectos Rosario — priorizar gastronómico y retail | C31: ALTA | D31: Gino / Juan | E31: ⬜ Pendiente
A32: 4 | B32: Crear plantilla de propuesta/presupuesto profesional | C32: MEDIA | D32: Gino / Juan | E32: ⬜ Pendiente
A33: 5 | B33: Definir política de adelanto en proyectos (30-50% al inicio) | C33: MEDIA | D33: Gino / Juan | E33: ⬜ Pendiente
A34: 6 | B34: Documentar flujo de trabajo: discovery → diseño → dev → revisión → entrega | C34: MEDIA | D34: Gino / Juan | E34: ⬜ Pendiente
A35: 7 | B35: Evaluar monotributo / formalización cuando la empresa escale | C35: BAJA | D35: Gino / Juan | E35: ⬜ Pendiente

Sheet 🤝 CRM (datos)
A1: PYRUX — Clientes activos | N1: URL producción | O1: Notas
A2: Actualizado: 27/03/2026
A4: # | B4: Empresa | C4: Referente / Contacto | D4: WhatsApp | E4: Email | F4: Plan | G4: Dev: precio lista | H4: Dev: descuento aplicado | I4: Dev: monto cobrado | J4: Mant./mes (USD) | K4: Inicio mantenimiento | L4: Próximo cobro | M4: Forma de cobro | N4: Contrato firmado | O4: Estado | P4: Notas internas
A5: 1 | B5: MedMind | C5: Guillermina Bassi | D5: 54 9 341 353-6452 | E5: guille.bassi@hotmail.com | F5: Mantenimiento activo | G5: $300 (proyecto personalizado) | H5: Sin descuento | I5: 300 | J5: 20 | K5: 46086 | L5: 46113 | M5: Débito automático MP | N5: NO ⚠️ | O5: Activo | P5: Primer cliente Pyrux. Sin contrato. Formalizar urgente.

Sheet 🛠️ Proyectos (datos)
A1: PYRUX — Proyectos
A2: Actualizado: 27/03/2026
A4: # | B4: Proyecto | C4: Cliente | D4: Tipo | E4: Plan | F4: Estado | G4: Entrega pactada | H4: URL producción | I4: Notas
A5: 1 | B5: MedMind | C5: MedMind | D5: Desarrollo + Mantenimiento | E5: Personalizado | F5: En producción ✓ | G5: A COMPLETAR | H5: medmind.com.ar | I5: Primer proyecto Pyrux. Mantenimiento activo $20/mes.
A6: 2 | B6: Portfolio Pyrux | C6: Pyrux (interno) | D6: Web institucional | E6: Propio | F6: En producción ✓ | G6: — | H6: pyrux.com.ar | I6: Web propia. Ver Goal Planner y MedMind como proyectos showcaseados.
A7: 3 | B7: Goal Planner | C7: Pyrux (interno) | D7: Aplicación web | E7: Propio | F7: En desarrollo | G7: A definir | H7: goalplanner.com.ar | I7: Producto interno Pyrux. Limpiar estructura de carpetas pendiente.

Sheet 💸 Finanzas (datos)
A1: PYRUX — Estado Financiero
A2: Actualizado: 27/03/2026
A4: ▸ INGRESOS RECURRENTES (MRR)
A5: Cliente | B5: Plan de mantenimiento | C5: Bruto/mes (USD) | D5: Comisión MP (1.52%) | E5: Neto/mes (USD) | F5: Fecha inicio | G5: Forma de cobro | H5: Estado | I5: Notas
A6: MedMind | B6: Mantenimiento | C6: 20 | D6: =C6*0.0152 -> 0.304 | E6: =C6-D6 -> 19.696 | F6: 46086 | G6: Débito MP | H6: Activo | I6: Sin contrato formal
A8: TOTALES MRR | C8: =SUM(C6:C7) -> 20 | D8: =SUM(D6:D7) -> 0.304 | E8: =SUM(E6:E7) -> 19.696
A10: ▸ INGRESOS POR PROYECTO (cobro único)
A11: Fecha | B11: Cliente | C11: Plan / Descripción | D11: Precio lista | E11: Descuento | F11: Monto cobrado (USD) | G11: % cobrado | H11: Saldo pendiente | I11: Estado | J11: Notas
A12: 2025 | B12: MedMind | C12: Desarrollo MedMind (app web) | D12: 300 | E12: Sin descuento | F12: 300 | G12: 1 | H12: 0 | I12: Cobrado | J12: Primer cliente Pyrux
A14: TOTAL PROYECTOS | F14: =IFERROR(SUM(F12:F13),0) -> 300
A16: ▸ GASTOS FIJOS MENSUALES
A17: Concepto | B17: USD/mes | C17: ARS equiv. | D17: Frecuencia | E17: Próximo vencimiento | F17: Notas
A18: Google Workspace (2 usuarios) | B18: 9.8 | C18: =B18*1420 -> 13916 | D18: Mensual | E18: Mensual | F18: $4.90 × 2 usuarios
A19: Claude Code | B19: 20 | C19: =B19*1420 -> 28400 | D19: Mensual | E19: Mensual | F19: 1 cuenta compartida Gino+Juan
A20: Dominios (3 × $8.500 ARS/año) | B20: 1.5 | C20: =B20*1420 -> 2130 | D20: Anual prorrateado | E20: Ver Config | F20: goalplanner / pyrux / medmind
A22: TOTAL GASTOS | B22: =B18+B19+B20 -> 31.3
A24: ▸ RESUMEN MENSUAL
A25: Métrica | B25: USD | C25: Observación
A26: MRR bruto | B26: =C8 -> 20
A27: Comisión Mercado Pago | B27: =ROUND(D8,3) -> 0.304 | C27: 1.52% del bruto
A28: MRR neto | B28: =ROUND(E8,3) -> 19.696
A29: Gastos fijos mensuales | B29: =B22 -> 31.3
A30: RESULTADO MENSUAL | B30: =ROUND(B28-B29,3) -> -11.604 | C30: Positivo = ganancia / Negativo = déficit
A31: RESULTADO ANUAL (proyectado) | B31: =ROUND(B30*12,3) -> -139.248
A33: ▸ BREAKEVEN Y OBJETIVOS
A34: Para cubrir gastos necesitás un MRR neto de: | B34: =B22 -> 31.3 | C34: USD/mes
A35: MRR neto actual: | B35: =ROUND(E8,3) -> 19.696 | C35: USD/mes
A36: Falta para breakeven: | B36: =ROUND(B34-B35,3) -> 11.604 | C36: USD/mes
A37: Estás en: | B37: =IF(B35>=B34,"SUPERÁVIT ✓","DÉFICIT") -> DÉFICIT
A39: ▸ PROYECCIÓN 6 MESES (clientes actuales, sin nuevos)
A40: Mes | B40: Ingresos recurrentes | C40: Gastos | D40: Resultado | E40: Acumulado
A41: 46113 | B41: =ROUND(E8,3) -> 19.696 | C41: =B22 -> 31.3 | D41: =ROUND(B41-C41,3) -> -11.604 | E41: =D41 -> -11.604
A42: 46143 | B42: =ROUND(E8,3) -> 19.696 | C42: =B22 -> 31.3 | D42: =ROUND(B42-C42,3) -> -11.604 | E42: =ROUND(E41+D42,3) -> -23.208
A43: 46174 | B43: =ROUND(E8,3) -> 19.696 | C43: =B22 -> 31.3 | D43: =ROUND(B43-C43,3) -> -11.604 | E43: =ROUND(E42+D43,3) -> -34.812
A44: 46204 | B44: =ROUND(E8,3) -> 19.696 | C44: =B22 -> 31.3 | D44: =ROUND(B44-C44,3) -> -11.604 | E44: =ROUND(E43+D44,3) -> -46.416
A45: 46235 | B45: =ROUND(E8,3) -> 19.696 | C45: =B22 -> 31.3 | D45: =ROUND(B45-C45,3) -> -11.604 | E45: =ROUND(E44+D45,3) -> -58.02
A46: 46266 | B46: =ROUND(E8,3) -> 19.696 | C46: =B22 -> 31.3 | D46: =ROUND(B46-C46,3) -> -11.604 | E46: =ROUND(E45+D46,3) -> -69.624

Sheet 📋 Prospectos Rosario
A1: PYRUX — Base de prospectos Rosario
A2: Actualizado: 27/03/2026 — 30 prospectos identificados
A4: Nombre del negocio | B4: Sector / Rubro | C4: Estado web | D4: Dirección / Zona | E4: Instagram | F4: Sitio web | G4: Por qué es prospecto | H4: Servicio sugerido | I4: Fuente | J4: Estado outreach | K4: Notas
A5: Estudio Priotti | B5: Estudio contable | C5: Web desactualizada | D5: Rosario centro | F5: estudiopriotti.com | G5: Sitio anticuado, sin SSL. Perfil profesional fuerte. | H5: Rediseño web + SSL | I5: Búsqueda Google | J5: Sin contactar
A6: Estudio Herusa | B6: Estudio contable | C6: Web desactualizada | D6: Rosario | F6: estudiocontableherusa.com.ar | G6: Sitio sin blog ni portal de clientes, diseño viejo. | H6: Rediseño + portal clientes | I6: Búsqueda Google | J6: Sin contactar
A7: Guastella & Asoc. | B7: Estudio contable | C7: Web desactualizada | D7: Rosario Santa Fe | F7: estudiocontablegya.com.ar | G7: 30+ años, sitio brochure sin actualizaciones. | H7: Rediseño web | I7: Búsqueda Google
A8: Frasesores | B8: Estudio contable | C8: Web desactualizada | D8: Rosario | F8: frasesores.com.ar | G8: Sitio con sistema de compra genérico, nada profesional. | H8: Rediseño completo | I8: Búsqueda Google | J8: Sin contactar
A9: Contador independiente CPCE II | B9: Estudio contable | C9: Sin web | D9: Rosario (múltiples) | G9: Miles de contadores matriculados sin web. Target masivo. | H9: Landing page profesional | I9: CPCE Cámara II | J9: Sin contactar
A10: Chiana & Cigno Estudio Jurídico | B10: Estudio jurídico | C10: Sin web | D10: Rosario Santa Fe | G10: Solo en directorio. Firma joven, diferenciación posible. | H10: Sitio institucional | I10: Legal.com.ar | J10: Sin contactar
A11: Moreira & Asociados | B11: Estudio jurídico | C11: Sin web | D11: Jujuy 1778 of.2 | G11: Sedes en Rosario, San Lorenzo y Casilda. Sin web propia. | H11: Sitio multi-sede | I11: Legal.com.ar | J11: Sin contactar
A12: Blando Figueroa y Asociados | B12: Estudio jurídico | C12: Sin web | D12: Rosario Santa Fe | G12: Solo directorio. Fuerte en penal, sin identidad digital. | H12: Sitio institucional | I12: Legal.com.ar | J12: Sin contactar
A13: Copes & Asociados | B13: Estudio jurídico | C13: Sin web | D13: Rosario Santa Fe | G13: Equipo de profesionales, cero presencia web propia. | H13: Sitio institucional | I13: Legal.com.ar | J13: Sin contactar
A14: V&C Estudio Jurídico | B14: Estudio jurídico | C14: Sin web | D14: Rosario + Arteaga | G14: Tres sedes. Oportunidad de CMS multi-sede. | H14: Sitio + CMS multi-sede | I14: Legal.com.ar | J14: Sin contactar
A15: Robiolo & Asociados | B15: Estudio jurídico | C15: Sin web | D15: Rosario Santa Fe | G15: Enfocados en empresas. Ticket alto potencial. | H15: Sitio institucional premium | I15: Legal.com.ar | J15: Sin contactar
A16: Centro de Estética Oroño | B16: Centro de estética | C16: Sin web | D16: Bv. Oroño, Rosario | E16: @esteticaorono | G16: 16K seguidores en IG. Alta demanda probada, sin web. | H16: Landing + sistema de turnos | I16: Instagram | J16: Sin contactar
A17: Mudra Rosario | B17: Centro de estética | C17: Sin web | D17: Rosario | E17: @mudrarosario | G17: Solo Instagram. Formato spa = ticket alto. | H17: Web + reservas online | I17: Instagram | J17: Sin contactar
A18: Kymè Studio | B18: Centro de estética | C18: Sin web | D18: Mariano Moreno 1739 | G18: 5★ en Fresha, muy buenas reseñas. Sin web propia. | H18: Landing + turnos | I18: Fresha | J18: Sin contactar
A19: Tania — El Amor Por Tu Piel | B19: Centro de estética | C19: Sin web | D19: Bv. Rondeau 1837 | G19: Buenas reseñas en Fresha, sin activo digital propio. | H19: Landing + reservas | I19: Fresha | J19: Sin contactar
A20: Estetica Médica Brarda | B20: Centro de estética | C20: Web desactualizada | D20: Rosario | F20: esteticamedicabrarda.com | G20: Sitio desactualizado, sin SSL. Procedimientos médicos. | H20: Rediseño + SSL + credenciales | I20: Búsqueda Google | J20: Pendiente
A21: @blush.rosario | B21: E-commerce / retail | C21: Sin web | D21: Rosario | E21: @blush.rosario | G21: 46K seguidores IG, venta solo por DM. Ideal tienda online. | H21: E-commerce / tienda online | I21: Instagram | J21: Pendiente
A22: GC Representaciones | B22: E-commerce / retail | C22: Sin web | D22: Rosario | E22: @gc.representaciones | G22: 37K seguidores. Venta por redes, gran oportunidad e-comm. | H22: Plataforma e-commerce | I22: Instagram | J22: Pendiente
A23: Serendipia Rosario | B23: E-commerce / retail | C23: Sin web | D23: Rosario | E23: @serendipia.rosario | G23: Activa en IG. Emprendimiento listo para escalar. | H23: Tienda online | I23: Instagram | J23: Pendiente
A24: Ferretarías / mueblerías barrio | B24: E-commerce / retail | C24: Sin web | D24: Rosario (varios) | G24: Sin link a sitio en directorio. Universo amplio. | H24: Landing + catálogo | I24: Directorio local | J24: Pendiente
A25: Excalibur (Holiday Inn) | B25: Gastronomía | C25: Web existente | D25: Dorrego 450, Centro | E25: @excaliburgourmet | F25: holidayinnrosario.com | G25: 4.7★ TripAdvisor, buen alcance digital pero puede crecer. | H25: Gestión RRSS + contenido | I25: TripAdvisor | J25: Pendiente
A26: Chinchibira | B26: Gastronomía | C26: Sin web | D26: Santiago 101, Pichincha | E26: @chinchibirabar | G26: Bar #1 TripAdvisor Rosario 2025. 4.6★, 950 opiniones. | H26: Web + RRSS + WhatsApp marketing | I26: TripAdvisor | J26: Pendiente
A27: Chicharra Asador | B27: Gastronomía | C27: Sin web | D27: Pueyrredón 1, Centro | E27: @chicharra_rosario | G27: 538 opiniones 4.4★. Sin web propia. | H27: Landing + reservas online | I27: TripAdvisor | J27: Pendiente
A28: Los Jardines (Bar & Grill) | B28: Gastronomía | C28: Web existente | D28: España y El Río, Costanera | E28: @losjardinesrosario | F28: losjardinesenrosario.com | G28: 770 opiniones 4.1★. Web existente, RRSS activo. | H28: Mejora web + CMS | I28: TripAdvisor | J28: Pendiente
A29: Vision Hair Studio | B29: Barbería | C29: Sin web | D29: Dorrego 90 PB, Centro | E29: @vision.hs_ | G29: 1.528 reviews 5.0★ en Fresha. Fuerte boca a boca. | H29: Landing + reservas + RRSS | I29: Fresha | J29: Pendiente
A30: Essenza Barbería | B30: Barbería | C30: Sin web | D30: Av. Provincias Unidas 815 | E30: @essenzabarberia | G30: 5.0★ Fresha 2026. Sin web, alta competencia en el rubro. | H30: Landing + sistema de turnos | I30: Fresha | J30: Pendiente
A31: Be and Feel (Estética) | B31: Centro de estética | C31: Sin web | D31: Entre Ríos 176, Centro | E31: @beandfeelrosario | G31: 13K seguidores IG activo. Sin web propia. | H31: Web + reservas + RRSS | I31: Instagram | J31: Pendiente
A32: CM Dental Rosario | B32: Salud / Odontología | C32: Web existente | D32: Paraguay 1227 PB | E32: @cmdentalrosario | F32: cmdentalrosario.com.ar | G32: Clínica moderna con web. Puede mejorar con SEO y contenido. | H32: Mejora web + SEO + CMS | I32: Google | J32: Pendiente
A33: O2 Gimnasio | B33: Fitness | C33: Web existente | D33: Av. Pellegrini 614 | E33: @o2gimnasio | F33: o2gimnasio.com.ar | G33: Presente en búsquedas locales. Web funcional. | H33: Mejora web + RRSS | I33: Google | J33: Pendiente
A34: Z Market (Ropa urbana) | B34: Moda / Comercio | C34: Web desactualizada | D34: Av. Santa Fe 2684 | E34: @zmarketrosario | F34: facebook.com/zmarketros | G34: Solo FB/IG activo. Sin tienda online propia. | H34: E-commerce / tienda online | I34: Instagram/Facebook | J34: Pendiente

Sheet ⚙️ Config
A1: PYRUX — Configuración global | D1: Última actualización: | E1: 46108
A3: PARÁMETROS FINANCIEROS | B3: Valor | C3: Unidad | D3: Notas
A4: Tipo de cambio USD → ARS (compra) | B4: 1425 | C4: ARS/USD | D4: Actualizar mensualmente
A5: Tipo de cambio USD → ARS (venta) | B5: 1415 | C5: ARS/USD | D5: Usar para convertir gastos en ARS
A6: Comisión Mercado Pago (débito automático) | B6: 0.0152 | C6: % | D6: 1.52% sobre cada cobro
A8: DESCUENTO DE LANZAMIENTO | B8: Valor
A9: Cupos totales | B9: 5 | C9: clientes | D9: 30% OFF en desarrollo (mantenimiento sin descuento)
A10: Cupos usados | B10: 0 | D10: Actualizar al cerrar cada cliente
A11: Cupos disponibles | B11: =B9-B10 -> 5
A13: GASTOS FIJOS MENSUALES | B13: USD/mes | C13: ARS equiv. | D13: Frecuencia | E13: Detalle
A14: Google Workspace (2 usuarios) | B14: 9.8 | C14: 13867 | D14: Mensual | E14: $4.90/usuario × 2
A15: Claude Code | B15: 20 | C15: 28300 | D15: Mensual | E15: Una cuenta compartida
A16: Dominios (amortización mensual) | B16: 1.5 | C16: 2125 | D16: Anual (prorrateado) | E16: 3 dominios × $8.500 ARS/año
A17: TOTAL GASTOS MENSUALES | B17: 31.3
A19: GASTOS ANUALES (dominios) | B19: ARS/año | C19: USD equiv. | D19: Vencimiento | E19: Dominio
A20: goalplanner.com.ar | B20: 8500 | C20: 6.01 | D20: 46430
A21: pyrux.com.ar | B21: 8500 | C21: 6.01 | D21: 46443
A22: medmind.com.ar | B22: 8500 | C22: 6.01 | D22: 46449
A23: TOTAL DOMINIOS ARS/año | B23: =B20+B21+B22 -> 25500 | C23: 18.02
A25: DATOS DE LA EMPRESA
A26: Nombre | B26: Pyrux
A27: Ciudad | B27: Rosario, Santa Fe
A28: Situación legal | B28: Informal (en negro) | D28: Formalizar al escalar
A29: WhatsApp | B29: A COMPLETAR
A30: Email | B30: ginorubengiorgi@pyrux.com.ar
A31: Instagram | B31: @pyrux_labs

Sheet 📦 Tarifario
A1: PYRUX — Tarifario de servicios
A2: Última actualización: 27/03/2026 | D2: Descuento lanzamiento 30% activo (mantenimiento sin descuento)
A4: ▸ PLANES ESTÁNDAR (sitios web)
A5: Plan | B5: Precio lista | C5: Precio c/descuento | D5: Mant./mes | E5: Entrega | F5: Respuesta soporte | G5: Incluye CMS
A6: Growth | B6: $300 USD | C6: $210 USD | D6: $40 USD | E6: 2 semanas | F6: 48hs | G6: No
A7: Pro | B7: $500 USD | C7: $350 USD | D7: $50 USD | E7: 3-4 semanas | F7: 48hs | G7: Sí
A8: Business | B8: Desde $800 USD | C8: Desde $560 USD | D8: $70 USD | E8: 4+ semanas | F8: 24hs | G8: Sí
A10: ▸ PLANES E-COMMERCE
A11: Plan | B11: Precio lista | C11: Precio c/descuento | D11: Mant./mes | E11: Entrega | F11: Respuesta soporte | G11: Incluye CMS
A12: E-Commerce Básico | B12: $800 USD | C12: $560 USD | D12: $50 USD | E12: 4 semanas | F12: 48hs | G12: Sí
A13: E-Commerce Pro | B13: $2.000 USD | C13: $1.400 USD | D13: $200 USD | E13: 6-8 semanas | F13: 24hs | G13: Sí
A14: E-Commerce Enterprise | B14: Consultar | C14: Consultar | D14: Consultar | E14: A convenir | F14: SLA dedicado | G14: Sí
A16: ▸ PERSONALIZADO (sistemas, IA, plataformas)
A17: Plan | B17: Precio lista | C17: Precio c/descuento | D17: Mant./mes | E17: Entrega | F17: Respuesta soporte
A18: Personalizado | B18: Consultar | C18: Consultar | D18: Consultar | E18: A definir | F18: A definir
A20: ▸ QUÉ INCLUYE CADA MANTENIMIENTO
A21: Incluye | B21: Growth ($40) | C21: Pro ($50) | D21: Business ($70)
A22: Hosting y SSL | B22: ✓ | C22: ✓ | D22: ✓
A23: Monitoreo 24/7 | B23: ✓ | C23: ✓ | D23: ✓
A24: Backup automático | B24: Mensual | C24: Semanal | D24: Semanal + retención extendida
A25: Cambios menores (textos, imágenes) | B25: ✓ | C25: ✓ | D25: ✓
A26: Actualizaciones de seguridad | B26: ✓ | C26: ✓ | D26: ✓
A27: Soporte técnico incluido | B27: Canal directo 48hs | C27: Hasta 2hs/mes, 48hs | D27: Hasta 4hs/mes, 24hs
A28: Reporte mensual de analíticas | B28: No | C28: ✓ | D28: ✓ Avanzado
A29: Actualizaciones y mejoras continuas | B29: No | C29: No | D29: ✓
A31: ▸ NOTAS COMERCIALES
A32: Moneda de cotización | B32: USD (pago en pesos al tipo de cambio del día o en dólares)
A33: Política de cobro (a definir) | B33: 30% adelanto + 70% a la entrega (PENDIENTE DEFINIR)
A34: Clientes de mantenimiento | B34: Cobro mensual por débito automático Mercado Pago
A35: Sin mantenimiento | B35: Se entrega el proyecto documentado y listo para administración propia
